{
 "bounds": [
  2196,
  2196
 ],
 "offset_for_id": [
  [
   "budapest_1",
   {
    "x": 898,
    "y": 1772
   }
  ],
  [
   "budapest_10",
   {
    "x": 639,
    "y": 598
   }
  ],
  [
   "budapest_100",
   {
    "x": 965,
    "y": 1772
   }
  ],
  [
   "budapest_101",
   {
    "x": 1729,
    "y": 583
   }
  ],
  [
   "budapest_102",
   {
    "x": 965,
    "y": 1910
   }
  ],
  [
   "budapest_103",
   {
    "x": 2195,
    "y": 815
   }
  ],
  [
   "budapest_104",
   {
    "x": 898,
    "y": 1143
   }
  ],
  [
   "budapest_105",
   {
    "x": 2193,
    "y": 850
   }
  ],
  [
   "budapest_106",
   {
    "x": 837,
    "y": 1730
   }
  ],
  [
   "budapest_107",
   {
    "x": 888,
    "y": 0
   }
  ],
  [
   "budapest_108",
   {
    "x": 1542,
    "y": 247
   }
  ],
  [
   "budapest_109",
   {
    "x": 1650,
    "y": 602
   }
  ],
  [
   "budapest_11",
   {
    "x": 266,
    "y": 1483
   }
  ],
  [
   "budapest_110",
   {
    "x": 1011,
    "y": 996
   }
  ],
  [
   "budapest_111",
   {
    "x": 897,
    "y": 2034
   }
  ],
  [
   "budapest_112",
   {
    "x": 538,
    "y": 1966
   }
  ],
  [
   "budapest_113",
   {
    "x": 744,
    "y": 1967
   }
  ],
  [
   "budapest_114",
   {
    "x": 2009,
    "y": 814
   }
  ],
  [
   "budapest_115",
   {
    "x": 727,
    "y": 1874
   }
  ],
  [
   "budapest_116",
   {
    "x": 2113,
    "y": 850
   }
  ],
  [
   "budapest_117",
   {
    "x": 240,
    "y": 2109
   }
  ],
  [
   "budapest_118",
   {
    "x": 202,
    "y": 1356
   }
  ],
  [
   "budapest_119",
   {
    "x": 1068,
    "y": 802
   }
  ],
  [
   "budapest_12",
   {
    "x": 994,
    "y": 356
   }
  ],
  [
   "budapest_120",
   {
    "x": 743,
    "y": 1704
   }
  ],
  [
   "budapest_121",
   {
    "x": 1988,
    "y": 353
   }
  ],
  [
   "budapest_122",
   {
    "x": 602,
    "y": 1107
   }
  ],
  [
   "budapest_123",
   {
    "x": 878,
    "y": 1502
   }
  ],
  [
   "budapest_124",
   {
    "x": 898,
    "y": 1287
   }
  ],
  [
   "budapest_125",
   {
    "x": 1533,
    "y": 850
   }
  ],
  [
   "budapest_126",
   {
    "x": 895,
    "y": 1158
   }
  ],
  [
   "budapest_127",
   {
    "x": 0,
    "y": 778
   }
  ],
  [
   "budapest_128",
   {
    "x": 1446,
    "y": 773
   }
  ],
  [
   "budapest_129",
   {
    "x": 1001,
    "y": 1287
   }
  ],
  [
   "budapest_13",
   {
    "x": 622,
    "y": 602
   }
  ],
  [
   "budapest_130",
   {
    "x": 898,
    "y": 996
   }
  ],
  [
   "budapest_131",
   {
    "x": 845,
    "y": 1967
   }
  ],
  [
   "budapest_132",
   {
    "x": 886,
    "y": 1836
   }
  ],
  [
   "budapest_133",
   {
    "x": 1645,
    "y": 247
   }
  ],
  [
   "budapest_134",
   {
    "x": 1758,
    "y": 775
   }
  ],
  [
   "budapest_135",
   {
    "x": 955,
    "y": 763
   }
  ],
  [
   "budapest_136",
   {
    "x": 1650,
    "y": 825
   }
  ],
  [
   "budapest_137",
   {
    "x": 0,
    "y": 1176
   }
  ],
  [
   "budapest_138",
   {
    "x": 973,
    "y": 1603
   }
  ],
  [
   "budapest_139",
   {
    "x": 890,
    "y": 513
   }
  ],
  [
   "budapest_14",
   {
    "x": 538,
    "y": 1809
   }
  ],
  [
   "budapest_140",
   {
    "x": 744,
    "y": 1360
   }
  ],
  [
   "budapest_141",
   {
    "x": 1667,
    "y": 333
   }
  ],
  [
   "budapest_142",
   {
    "x": 240,
    "y": 2078
   }
  ],
  [
   "budapest_143",
   {
    "x": 845,
    "y": 2081
   }
  ],
  [
   "budapest_144",
   {
    "x": 744,
    "y": 996
   }
  ],
  [
   "budapest_145",
   {
    "x": 845,
    "y": 2132
   }
  ],
  [
   "budapest_146",
   {
    "x": 1152,
    "y": 981
   }
  ],
  [
   "budapest_147",
   {
    "x": 1667,
    "y": 0
   }
  ],
  [
   "budapest_148",
   {
    "x": 842,
    "y": 763
   }
  ],
  [
   "budapest_149",
   {
    "x": 897,
    "y": 2132
   }
  ],
  [
   "budapest_15",
   {
    "x": 1988,
    "y": 0
   }
  ],
  [
   "budapest_150",
   {
    "x": 240,
    "y": 2159
   }
  ],
  [
   "budapest_151",
   {
    "x": 1024,
    "y": 849
   }
  ],
  [
   "budapest_152",
   {
    "x": 1542,
    "y": 341
   }
  ],
  [
   "budapest_153",
   {
    "x": 1855,
    "y": 850
   }
  ],
  [
   "budapest_154",
   {
    "x": 240,
    "y": 2139
   }
  ],
  [
   "budapest_155",
   {
    "x": 550,
    "y": 1630
   }
  ],
  [
   "budapest_156",
   {
    "x": 898,
    "y": 2035
   }
  ],
  [
   "budapest_157",
   {
    "x": 604,
    "y": 1450
   }
  ],
  [
   "budapest_158",
   {
    "x": 0,
    "y": 1540
   }
  ],
  [
   "budapest_159",
   {
    "x": 744,
    "y": 1836
   }
  ],
  [
   "budapest_16",
   {
    "x": 0,
    "y": 356
   }
  ],
  [
   "budapest_160",
   {
    "x": 450,
    "y": 278
   }
  ],
  [
   "budapest_161",
   {
    "x": 1729,
    "y": 356
   }
  ],
  [
   "budapest_162",
   {
    "x": 1280,
    "y": 602
   }
  ],
  [
   "budapest_163",
   {
    "x": 912,
    "y": 763
   }
  ],
  [
   "budapest_164",
   {
    "x": 742,
    "y": 1450
   }
  ],
  [
   "budapest_165",
   {
    "x": 604,
    "y": 2050
   }
  ],
  [
   "budapest_166",
   {
    "x": 1446,
    "y": 602
   }
  ],
  [
   "budapest_167",
   {
    "x": 1967,
    "y": 356
   }
  ],
  [
   "budapest_168",
   {
    "x": 202,
    "y": 1176
   }
  ],
  [
   "budapest_169",
   {
    "x": 837,
    "y": 1656
   }
  ],
  [
   "budapest_17",
   {
    "x": 1074,
    "y": 602
   }
  ],
  [
   "budapest_170",
   {
    "x": 1954,
    "y": 808
   }
  ],
  [
   "budapest_171",
   {
    "x": 1512,
    "y": 356
   }
  ],
  [
   "budapest_172",
   {
    "x": 1257,
    "y": 356
   }
  ],
  [
   "budapest_173",
   {
    "x": 2009,
    "y": 602
   }
  ],
  [
   "budapest_174",
   {
    "x": 744,
    "y": 1502
   }
  ],
  [
   "budapest_175",
   {
    "x": 842,
    "y": 602
   }
  ],
  [
   "budapest_176",
   {
    "x": 1988,
    "y": 291
   }
  ],
  [
   "budapest_177",
   {
    "x": 1010,
    "y": 1603
   }
  ],
  [
   "budapest_178",
   {
    "x": 2135,
    "y": 571
   }
  ],
  [
   "budapest_179",
   {
    "x": 531,
    "y": 278
   }
  ],
  [
   "budapest_18",
   {
    "x": 1681,
    "y": 850
   }
  ],
  [
   "budapest_180",
   {
    "x": 1257,
    "y": 535
   }
  ],
  [
   "budapest_181",
   {
    "x": 744,
    "y": 2127
   }
  ],
  [
   "budapest_182",
   {
    "x": 1074,
    "y": 786
   }
  ],
  [
   "budapest_183",
   {
    "x": 2099,
    "y": 773
   }
  ],
  [
   "budapest_184",
   {
    "x": 1530,
    "y": 773
   }
  ],
  [
   "budapest_185",
   {
    "x": 1683,
    "y": 601
   }
  ],
  [
   "budapest_186",
   {
    "x": 1244,
    "y": 338
   }
  ],
  [
   "budapest_187",
   {
    "x": 2099,
    "y": 815
   }
  ],
  [
   "budapest_19",
   {
    "x": 266,
    "y": 1809
   }
  ],
  [
   "budapest_2",
   {
    "x": 1996,
    "y": 995
   }
  ],
  [
   "budapest_20",
   {
    "x": 1204,
    "y": 786
   }
  ],
  [
   "budapest_21",
   {
    "x": 1040,
    "y": 763
   }
  ],
  [
   "budapest_22",
   {
    "x": 1133,
    "y": 1085
   }
  ],
  [
   "budapest_23",
   {
    "x": 0,
    "y": 2078
   }
  ],
  [
   "budapest_24",
   {
    "x": 1152,
    "y": 850
   }
  ],
  [
   "budapest_25",
   {
    "x": 767,
    "y": 778
   }
  ],
  [
   "budapest_26",
   {
    "x": 1512,
    "y": 570
   }
  ],
  [
   "budapest_27",
   {
    "x": 2135,
    "y": 356
   }
  ],
  [
   "budapest_28",
   {
    "x": 604,
    "y": 850
   }
  ],
  [
   "budapest_29",
   {
    "x": 1530,
    "y": 815
   }
  ],
  [
   "budapest_3",
   {
    "x": 0,
    "y": 2188
   }
  ],
  [
   "budapest_30",
   {
    "x": 639,
    "y": 356
   }
  ],
  [
   "budapest_31",
   {
    "x": 266,
    "y": 850
   }
  ],
  [
   "budapest_32",
   {
    "x": 1401,
    "y": 247
   }
  ],
  [
   "budapest_33",
   {
    "x": 2195,
    "y": 356
   }
  ],
  [
   "budapest_34",
   {
    "x": 1232,
    "y": 565
   }
  ],
  [
   "budapest_35",
   {
    "x": 0,
    "y": 1838
   }
  ],
  [
   "budapest_36",
   {
    "x": 898,
    "y": 1440
   }
  ],
  [
   "budapest_37",
   {
    "x": 1851,
    "y": 808
   }
  ],
  [
   "budapest_38",
   {
    "x": 1024,
    "y": 802
   }
  ],
  [
   "budapest_39",
   {
    "x": 898,
    "y": 1603
   }
  ],
  [
   "budapest_4",
   {
    "x": 1384,
    "y": 535
   }
  ],
  [
   "budapest_40",
   {
    "x": 1829,
    "y": 526
   }
  ],
  [
   "budapest_41",
   {
    "x": 266,
    "y": 356
   }
  ],
  [
   "budapest_42",
   {
    "x": 622,
    "y": 778
   }
  ],
  [
   "budapest_43",
   {
    "x": 898,
    "y": 1932
   }
  ],
  [
   "budapest_44",
   {
    "x": 952,
    "y": 850
   }
  ],
  [
   "budapest_45",
   {
    "x": 604,
    "y": 1704
   }
  ],
  [
   "budapest_46",
   {
    "x": 266,
    "y": 1291
   }
  ],
  [
   "budapest_47",
   {
    "x": 1967,
    "y": 593
   }
  ],
  [
   "budapest_48",
   {
    "x": 1996,
    "y": 850
   }
  ],
  [
   "budapest_49",
   {
    "x": 1509,
    "y": 535
   }
  ],
  [
   "budapest_5",
   {
    "x": 842,
    "y": 2127
   }
  ],
  [
   "budapest_50",
   {
    "x": 744,
    "y": 850
   }
  ],
  [
   "budapest_51",
   {
    "x": 1133,
    "y": 996
   }
  ],
  [
   "budapest_52",
   {
    "x": 1916,
    "y": 526
   }
  ],
  [
   "budapest_53",
   {
    "x": 266,
    "y": 2116
   }
  ],
  [
   "budapest_54",
   {
    "x": 266,
    "y": 1630
   }
  ],
  [
   "budapest_55",
   {
    "x": 1244,
    "y": 0
   }
  ],
  [
   "budapest_56",
   {
    "x": 1851,
    "y": 602
   }
  ],
  [
   "budapest_57",
   {
    "x": 898,
    "y": 2159
   }
  ],
  [
   "budapest_58",
   {
    "x": 838,
    "y": 1158
   }
  ],
  [
   "budapest_59",
   {
    "x": 1352,
    "y": 850
   }
  ],
  [
   "budapest_6",
   {
    "x": 0,
    "y": 0
   }
  ],
  [
   "budapest_60",
   {
    "x": 434,
    "y": 2116
   }
  ],
  [
   "budapest_61",
   {
    "x": 1712,
    "y": 333
   }
  ],
  [
   "budapest_62",
   {
    "x": 51,
    "y": 2188
   }
  ],
  [
   "budapest_63",
   {
    "x": 639,
    "y": 513
   }
  ],
  [
   "budapest_64",
   {
    "x": 1182,
    "y": 565
   }
  ],
  [
   "budapest_65",
   {
    "x": 538,
    "y": 1910
   }
  ],
  [
   "budapest_66",
   {
    "x": 994,
    "y": 565
   }
  ],
  [
   "budapest_67",
   {
    "x": 845,
    "y": 2174
   }
  ],
  [
   "budapest_68",
   {
    "x": 1789,
    "y": 583
   }
  ],
  [
   "budapest_69",
   {
    "x": 266,
    "y": 2195
   }
  ],
  [
   "budapest_7",
   {
    "x": 450,
    "y": 0
   }
  ],
  [
   "budapest_70",
   {
    "x": 2009,
    "y": 773
   }
  ],
  [
   "budapest_71",
   {
    "x": 897,
    "y": 1360
   }
  ],
  [
   "budapest_72",
   {
    "x": 965,
    "y": 1834
   }
  ],
  [
   "budapest_73",
   {
    "x": 1621,
    "y": 570
   }
  ],
  [
   "budapest_74",
   {
    "x": 845,
    "y": 2034
   }
  ],
  [
   "budapest_75",
   {
    "x": 1683,
    "y": 570
   }
  ],
  [
   "budapest_76",
   {
    "x": 266,
    "y": 1977
   }
  ],
  [
   "budapest_77",
   {
    "x": 593,
    "y": 1483
   }
  ],
  [
   "budapest_78",
   {
    "x": 266,
    "y": 1107
   }
  ],
  [
   "budapest_79",
   {
    "x": 1729,
    "y": 526
   }
  ],
  [
   "budapest_8",
   {
    "x": 604,
    "y": 1141
   }
  ],
  [
   "budapest_80",
   {
    "x": 1650,
    "y": 775
   }
  ],
  [
   "budapest_81",
   {
    "x": 531,
    "y": 324
   }
  ],
  [
   "budapest_82",
   {
    "x": 1204,
    "y": 848
   }
  ],
  [
   "budapest_83",
   {
    "x": 261,
    "y": 1838
   }
  ],
  [
   "budapest_84",
   {
    "x": 994,
    "y": 601
   }
  ],
  [
   "budapest_85",
   {
    "x": 980,
    "y": 513
   }
  ],
  [
   "budapest_86",
   {
    "x": 565,
    "y": 2012
   }
  ],
  [
   "budapest_87",
   {
    "x": 1735,
    "y": 333
   }
  ],
  [
   "budapest_88",
   {
    "x": 251,
    "y": 1540
   }
  ],
  [
   "budapest_89",
   {
    "x": 1257,
    "y": 601
   }
  ],
  [
   "budapest_9",
   {
    "x": 201,
    "y": 778
   }
  ],
  [
   "budapest_90",
   {
    "x": 2113,
    "y": 919
   }
  ],
  [
   "budapest_91",
   {
    "x": 604,
    "y": 1874
   }
  ],
  [
   "budapest_92",
   {
    "x": 965,
    "y": 1873
   }
  ],
  [
   "budapest_93",
   {
    "x": 955,
    "y": 802
   }
  ],
  [
   "budapest_94",
   {
    "x": 2093,
    "y": 291
   }
  ],
  [
   "budapest_95",
   {
    "x": 744,
    "y": 1656
   }
  ],
  [
   "budapest_96",
   {
    "x": 744,
    "y": 1158
   }
  ],
  [
   "budapest_97",
   {
    "x": 1244,
    "y": 247
   }
  ],
  [
   "budapest_98",
   {
    "x": 565,
    "y": 1977
   }
  ],
  [
   "budapest_99",
   {
    "x": 266,
    "y": 602
   }
  ]
 ],
 "parameters": {
  "bin": "BNF",
  "pack": "GuillotineBssfMinas",
  "sort": "SORT_PERI"
 },
 "summary": {
  "id": "BNF/GuillotineBssfMinas/SORT_PERI",
  "name": "BNF/GuillotineBssfMinas/SORT_PERI",
  "place_id": "budapest"
 }
}