{
 "bounds": [
  1736,
  1597
 ],
 "offset_for_id": [
  [
   "edinburgh_1",
   {
    "x": 127,
    "y": 1360
   }
  ],
  [
   "edinburgh_10",
   {
    "x": 1113,
    "y": 779
   }
  ],
  [
   "edinburgh_100",
   {
    "x": 1214,
    "y": 1015
   }
  ],
  [
   "edinburgh_101",
   {
    "x": 709,
    "y": 171
   }
  ],
  [
   "edinburgh_102",
   {
    "x": 1220,
    "y": 1019
   }
  ],
  [
   "edinburgh_103",
   {
    "x": 498,
    "y": 1288
   }
  ],
  [
   "edinburgh_104",
   {
    "x": 1579,
    "y": 394
   }
  ],
  [
   "edinburgh_105",
   {
    "x": 0,
    "y": 934
   }
  ],
  [
   "edinburgh_106",
   {
    "x": 1580,
    "y": 394
   }
  ],
  [
   "edinburgh_107",
   {
    "x": 1113,
    "y": 767
   }
  ],
  [
   "edinburgh_108",
   {
    "x": 828,
    "y": 1173
   }
  ],
  [
   "edinburgh_109",
   {
    "x": 1138,
    "y": 769
   }
  ],
  [
   "edinburgh_11",
   {
    "x": 1444,
    "y": 278
   }
  ],
  [
   "edinburgh_110",
   {
    "x": 1668,
    "y": 217
   }
  ],
  [
   "edinburgh_111",
   {
    "x": 559,
    "y": 848
   }
  ],
  [
   "edinburgh_112",
   {
    "x": 939,
    "y": 886
   }
  ],
  [
   "edinburgh_113",
   {
    "x": 0,
    "y": 1114
   }
  ],
  [
   "edinburgh_114",
   {
    "x": 215,
    "y": 1362
   }
  ],
  [
   "edinburgh_115",
   {
    "x": 1220,
    "y": 1023
   }
  ],
  [
   "edinburgh_116",
   {
    "x": 246,
    "y": 469
   }
  ],
  [
   "edinburgh_117",
   {
    "x": 356,
    "y": 978
   }
  ],
  [
   "edinburgh_118",
   {
    "x": 1222,
    "y": 1023
   }
  ],
  [
   "edinburgh_119",
   {
    "x": 168,
    "y": 1114
   }
  ],
  [
   "edinburgh_12",
   {
    "x": 1161,
    "y": 1116
   }
  ],
  [
   "edinburgh_120",
   {
    "x": 349,
    "y": 1157
   }
  ],
  [
   "edinburgh_121",
   {
    "x": 660,
    "y": 1117
   }
  ],
  [
   "edinburgh_122",
   {
    "x": 1236,
    "y": 1032
   }
  ],
  [
   "edinburgh_123",
   {
    "x": 709,
    "y": 804
   }
  ],
  [
   "edinburgh_124",
   {
    "x": 635,
    "y": 1237
   }
  ],
  [
   "edinburgh_125",
   {
    "x": 1668,
    "y": 88
   }
  ],
  [
   "edinburgh_126",
   {
    "x": 1135,
    "y": 779
   }
  ],
  [
   "edinburgh_127",
   {
    "x": 1186,
    "y": 271
   }
  ],
  [
   "edinburgh_128",
   {
    "x": 1214,
    "y": 1025
   }
  ],
  [
   "edinburgh_129",
   {
    "x": 883,
    "y": 347
   }
  ],
  [
   "edinburgh_13",
   {
    "x": 1689,
    "y": 0
   }
  ],
  [
   "edinburgh_130",
   {
    "x": 925,
    "y": 171
   }
  ],
  [
   "edinburgh_131",
   {
    "x": 0,
    "y": 0
   }
  ],
  [
   "edinburgh_132",
   {
    "x": 356,
    "y": 848
   }
  ],
  [
   "edinburgh_133",
   {
    "x": 1500,
    "y": 198
   }
  ],
  [
   "edinburgh_134",
   {
    "x": 1320,
    "y": 278
   }
  ],
  [
   "edinburgh_135",
   {
    "x": 1113,
    "y": 717
   }
  ],
  [
   "edinburgh_136",
   {
    "x": 925,
    "y": 273
   }
  ],
  [
   "edinburgh_137",
   {
    "x": 502,
    "y": 1288
   }
  ],
  [
   "edinburgh_138",
   {
    "x": 1458,
    "y": 762
   }
  ],
  [
   "edinburgh_139",
   {
    "x": 879,
    "y": 951
   }
  ],
  [
   "edinburgh_14",
   {
    "x": 509,
    "y": 1288
   }
  ],
  [
   "edinburgh_140",
   {
    "x": 1138,
    "y": 775
   }
  ],
  [
   "edinburgh_141",
   {
    "x": 939,
    "y": 784
   }
  ],
  [
   "edinburgh_142",
   {
    "x": 1324,
    "y": 802
   }
  ],
  [
   "edinburgh_143",
   {
    "x": 1257,
    "y": 520
   }
  ],
  [
   "edinburgh_144",
   {
    "x": 481,
    "y": 1056
   }
  ],
  [
   "edinburgh_145",
   {
    "x": 958,
    "y": 124
   }
  ],
  [
   "edinburgh_146",
   {
    "x": 1138,
    "y": 767
   }
  ],
  [
   "edinburgh_147",
   {
    "x": 1137,
    "y": 779
   }
  ],
  [
   "edinburgh_15",
   {
    "x": 0,
    "y": 183
   }
  ],
  [
   "edinburgh_16",
   {
    "x": 204,
    "y": 1428
   }
  ],
  [
   "edinburgh_17",
   {
    "x": 1378,
    "y": 0
   }
  ],
  [
   "edinburgh_18",
   {
    "x": 921,
    "y": 515
   }
  ],
  [
   "edinburgh_19",
   {
    "x": 1453,
    "y": 631
   }
  ],
  [
   "edinburgh_2",
   {
    "x": 1324,
    "y": 993
   }
  ],
  [
   "edinburgh_20",
   {
    "x": 91,
    "y": 1491
   }
  ],
  [
   "edinburgh_21",
   {
    "x": 1350,
    "y": 631
   }
  ],
  [
   "edinburgh_22",
   {
    "x": 1370,
    "y": 137
   }
  ],
  [
   "edinburgh_23",
   {
    "x": 481,
    "y": 978
   }
  ],
  [
   "edinburgh_24",
   {
    "x": 709,
    "y": 347
   }
  ],
  [
   "edinburgh_25",
   {
    "x": 436,
    "y": 1294
   }
  ],
  [
   "edinburgh_26",
   {
    "x": 1257,
    "y": 271
   }
  ],
  [
   "edinburgh_27",
   {
    "x": 1575,
    "y": 394
   }
  ],
  [
   "edinburgh_28",
   {
    "x": 459,
    "y": 469
   }
  ],
  [
   "edinburgh_29",
   {
    "x": 914,
    "y": 784
   }
  ],
  [
   "edinburgh_3",
   {
    "x": 682,
    "y": 171
   }
  ],
  [
   "edinburgh_30",
   {
    "x": 1218,
    "y": 1025
   }
  ],
  [
   "edinburgh_31",
   {
    "x": 1033,
    "y": 1116
   }
  ],
  [
   "edinburgh_32",
   {
    "x": 0,
    "y": 1524
   }
  ],
  [
   "edinburgh_33",
   {
    "x": 1320,
    "y": 412
   }
  ],
  [
   "edinburgh_34",
   {
    "x": 1007,
    "y": 1191
   }
  ],
  [
   "edinburgh_35",
   {
    "x": 1139,
    "y": 385
   }
  ],
  [
   "edinburgh_36",
   {
    "x": 698,
    "y": 951
   }
  ],
  [
   "edinburgh_37",
   {
    "x": 1530,
    "y": 0
   }
  ],
  [
   "edinburgh_38",
   {
    "x": 1350,
    "y": 762
   }
  ],
  [
   "edinburgh_39",
   {
    "x": 1161,
    "y": 1164
   }
  ],
  [
   "edinburgh_4",
   {
    "x": 914,
    "y": 649
   }
  ],
  [
   "edinburgh_40",
   {
    "x": 1151,
    "y": 775
   }
  ],
  [
   "edinburgh_41",
   {
    "x": 498,
    "y": 1117
   }
  ],
  [
   "edinburgh_42",
   {
    "x": 1160,
    "y": 717
   }
  ],
  [
   "edinburgh_43",
   {
    "x": 921,
    "y": 385
   }
  ],
  [
   "edinburgh_44",
   {
    "x": 343,
    "y": 700
   }
  ],
  [
   "edinburgh_45",
   {
    "x": 1318,
    "y": 520
   }
  ],
  [
   "edinburgh_46",
   {
    "x": 680,
    "y": 469
   }
  ],
  [
   "edinburgh_47",
   {
    "x": 743,
    "y": 1230
   }
  ],
  [
   "edinburgh_48",
   {
    "x": 1378,
    "y": 114
   }
  ],
  [
   "edinburgh_49",
   {
    "x": 1033,
    "y": 1041
   }
  ],
  [
   "edinburgh_5",
   {
    "x": 706,
    "y": 1056
   }
  ],
  [
   "edinburgh_50",
   {
    "x": 1220,
    "y": 1015
   }
  ],
  [
   "edinburgh_51",
   {
    "x": 828,
    "y": 1113
   }
  ],
  [
   "edinburgh_52",
   {
    "x": 335,
    "y": 1294
   }
  ],
  [
   "edinburgh_53",
   {
    "x": 1324,
    "y": 874
   }
  ],
  [
   "edinburgh_54",
   {
    "x": 204,
    "y": 1364
   }
  ],
  [
   "edinburgh_55",
   {
    "x": 1481,
    "y": 512
   }
  ],
  [
   "edinburgh_56",
   {
    "x": 1127,
    "y": 779
   }
  ],
  [
   "edinburgh_57",
   {
    "x": 1218,
    "y": 1032
   }
  ],
  [
   "edinburgh_58",
   {
    "x": 1581,
    "y": 272
   }
  ],
  [
   "edinburgh_59",
   {
    "x": 0,
    "y": 444
   }
  ],
  [
   "edinburgh_6",
   {
    "x": 1500,
    "y": 114
   }
  ],
  [
   "edinburgh_60",
   {
    "x": 958,
    "y": 0
   }
  ],
  [
   "edinburgh_61",
   {
    "x": 1007,
    "y": 1173
   }
  ],
  [
   "edinburgh_62",
   {
    "x": 1186,
    "y": 137
   }
  ],
  [
   "edinburgh_63",
   {
    "x": 1127,
    "y": 767
   }
  ],
  [
   "edinburgh_64",
   {
    "x": 1575,
    "y": 395
   }
  ],
  [
   "edinburgh_65",
   {
    "x": 682,
    "y": 0
   }
  ],
  [
   "edinburgh_66",
   {
    "x": 0,
    "y": 1409
   }
  ],
  [
   "edinburgh_67",
   {
    "x": 1194,
    "y": 0
   }
  ],
  [
   "edinburgh_68",
   {
    "x": 1128,
    "y": 589
   }
  ],
  [
   "edinburgh_69",
   {
    "x": 0,
    "y": 1242
   }
  ],
  [
   "edinburgh_7",
   {
    "x": 305,
    "y": 1373
   }
  ],
  [
   "edinburgh_70",
   {
    "x": 1204,
    "y": 1027
   }
  ],
  [
   "edinburgh_71",
   {
    "x": 911,
    "y": 1173
   }
  ],
  [
   "edinburgh_72",
   {
    "x": 1225,
    "y": 902
   }
  ],
  [
   "edinburgh_73",
   {
    "x": 459,
    "y": 681
   }
  ],
  [
   "edinburgh_74",
   {
    "x": 879,
    "y": 1041
   }
  ],
  [
   "edinburgh_75",
   {
    "x": 709,
    "y": 631
   }
  ],
  [
   "edinburgh_76",
   {
    "x": 911,
    "y": 1227
   }
  ],
  [
   "edinburgh_77",
   {
    "x": 1145,
    "y": 767
   }
  ],
  [
   "edinburgh_78",
   {
    "x": 204,
    "y": 1360
   }
  ],
  [
   "edinburgh_79",
   {
    "x": 1154,
    "y": 769
   }
  ],
  [
   "edinburgh_8",
   {
    "x": 498,
    "y": 1237
   }
  ],
  [
   "edinburgh_80",
   {
    "x": 1092,
    "y": 902
   }
  ],
  [
   "edinburgh_81",
   {
    "x": 1145,
    "y": 768
   }
  ],
  [
   "edinburgh_82",
   {
    "x": 181,
    "y": 934
   }
  ],
  [
   "edinburgh_83",
   {
    "x": 0,
    "y": 711
   }
  ],
  [
   "edinburgh_84",
   {
    "x": 1217,
    "y": 1025
   }
  ],
  [
   "edinburgh_85",
   {
    "x": 1217,
    "y": 1026
   }
  ],
  [
   "edinburgh_86",
   {
    "x": 178,
    "y": 711
   }
  ],
  [
   "edinburgh_87",
   {
    "x": 212,
    "y": 1360
   }
  ],
  [
   "edinburgh_88",
   {
    "x": 1444,
    "y": 394
   }
  ],
  [
   "edinburgh_89",
   {
    "x": 208,
    "y": 1360
   }
  ],
  [
   "edinburgh_9",
   {
    "x": 1092,
    "y": 1006
   }
  ],
  [
   "edinburgh_90",
   {
    "x": 217,
    "y": 1251
   }
  ],
  [
   "edinburgh_91",
   {
    "x": 1146,
    "y": 717
   }
  ],
  [
   "edinburgh_92",
   {
    "x": 1214,
    "y": 1006
   }
  ],
  [
   "edinburgh_93",
   {
    "x": 1577,
    "y": 394
   }
  ],
  [
   "edinburgh_94",
   {
    "x": 418,
    "y": 183
   }
  ],
  [
   "edinburgh_95",
   {
    "x": 217,
    "y": 1094
   }
  ],
  [
   "edinburgh_96",
   {
    "x": 1578,
    "y": 394
   }
  ],
  [
   "edinburgh_97",
   {
    "x": 1160,
    "y": 802
   }
  ],
  [
   "edinburgh_98",
   {
    "x": 215,
    "y": 1360
   }
  ],
  [
   "edinburgh_99",
   {
    "x": 1204,
    "y": 1006
   }
  ]
 ],
 "parameters": {
  "bin": "BNF",
  "pack": "MaxRectsBlsf",
  "sort": "SORT_PERI"
 },
 "summary": {
  "id": "BNF/MaxRectsBlsf/SORT_PERI",
  "name": "BNF/MaxRectsBlsf/SORT_PERI",
  "place_id": "edinburgh"
 }
}