{
 "bounds": [
  1736,
  1736
 ],
 "offset_for_id": [
  [
   "edinburgh_1",
   {
    "x": 933,
    "y": 1551
   }
  ],
  [
   "edinburgh_10",
   {
    "x": 1213,
    "y": 764
   }
  ],
  [
   "edinburgh_100",
   {
    "x": 1442,
    "y": 717
   }
  ],
  [
   "edinburgh_101",
   {
    "x": 1199,
    "y": 0
   }
  ],
  [
   "edinburgh_102",
   {
    "x": 1731,
    "y": 979
   }
  ],
  [
   "edinburgh_103",
   {
    "x": 1443,
    "y": 761
   }
  ],
  [
   "edinburgh_104",
   {
    "x": 1266,
    "y": 765
   }
  ],
  [
   "edinburgh_105",
   {
    "x": 221,
    "y": 1228
   }
  ],
  [
   "edinburgh_106",
   {
    "x": 1266,
    "y": 766
   }
  ],
  [
   "edinburgh_107",
   {
    "x": 1251,
    "y": 746
   }
  ],
  [
   "edinburgh_108",
   {
    "x": 800,
    "y": 998
   }
  ],
  [
   "edinburgh_109",
   {
    "x": 871,
    "y": 1475
   }
  ],
  [
   "edinburgh_11",
   {
    "x": 1498,
    "y": 769
   }
  ],
  [
   "edinburgh_110",
   {
    "x": 933,
    "y": 1682
   }
  ],
  [
   "edinburgh_111",
   {
    "x": 800,
    "y": 769
   }
  ],
  [
   "edinburgh_112",
   {
    "x": 250,
    "y": 1440
   }
  ],
  [
   "edinburgh_113",
   {
    "x": 250,
    "y": 1595
   }
  ],
  [
   "edinburgh_114",
   {
    "x": 1264,
    "y": 763
   }
  ],
  [
   "edinburgh_115",
   {
    "x": 1264,
    "y": 765
   }
  ],
  [
   "edinburgh_116",
   {
    "x": 0,
    "y": 997
   }
  ],
  [
   "edinburgh_117",
   {
    "x": 418,
    "y": 490
   }
  ],
  [
   "edinburgh_118",
   {
    "x": 1264,
    "y": 767
   }
  ],
  [
   "edinburgh_119",
   {
    "x": 733,
    "y": 1044
   }
  ],
  [
   "edinburgh_12",
   {
    "x": 1609,
    "y": 955
   }
  ],
  [
   "edinburgh_120",
   {
    "x": 802,
    "y": 612
   }
  ],
  [
   "edinburgh_121",
   {
    "x": 1448,
    "y": 612
   }
  ],
  [
   "edinburgh_122",
   {
    "x": 1620,
    "y": 0
   }
  ],
  [
   "edinburgh_123",
   {
    "x": 418,
    "y": 183
   }
  ],
  [
   "edinburgh_124",
   {
    "x": 291,
    "y": 648
   }
  ],
  [
   "edinburgh_125",
   {
    "x": 1010,
    "y": 1551
   }
  ],
  [
   "edinburgh_126",
   {
    "x": 1734,
    "y": 955
   }
  ],
  [
   "edinburgh_127",
   {
    "x": 800,
    "y": 1192
   }
  ],
  [
   "edinburgh_128",
   {
    "x": 1264,
    "y": 761
   }
  ],
  [
   "edinburgh_129",
   {
    "x": 1213,
    "y": 732
   }
  ],
  [
   "edinburgh_13",
   {
    "x": 1470,
    "y": 578
   }
  ],
  [
   "edinburgh_130",
   {
    "x": 593,
    "y": 330
   }
  ],
  [
   "edinburgh_131",
   {
    "x": 0,
    "y": 0
   }
  ],
  [
   "edinburgh_132",
   {
    "x": 1520,
    "y": 183
   }
  ],
  [
   "edinburgh_133",
   {
    "x": 933,
    "y": 955
   }
  ],
  [
   "edinburgh_134",
   {
    "x": 670,
    "y": 910
   }
  ],
  [
   "edinburgh_135",
   {
    "x": 1683,
    "y": 955
   }
  ],
  [
   "edinburgh_136",
   {
    "x": 866,
    "y": 183
   }
  ],
  [
   "edinburgh_137",
   {
    "x": 1443,
    "y": 765
   }
  ],
  [
   "edinburgh_138",
   {
    "x": 246,
    "y": 953
   }
  ],
  [
   "edinburgh_139",
   {
    "x": 871,
    "y": 1395
   }
  ],
  [
   "edinburgh_14",
   {
    "x": 1620,
    "y": 132
   }
  ],
  [
   "edinburgh_140",
   {
    "x": 1251,
    "y": 758
   }
  ],
  [
   "edinburgh_141",
   {
    "x": 1412,
    "y": 330
   }
  ],
  [
   "edinburgh_142",
   {
    "x": 1101,
    "y": 955
   }
  ],
  [
   "edinburgh_143",
   {
    "x": 863,
    "y": 1192
   }
  ],
  [
   "edinburgh_144",
   {
    "x": 933,
    "y": 894
   }
  ],
  [
   "edinburgh_145",
   {
    "x": 1011,
    "y": 565
   }
  ],
  [
   "edinburgh_146",
   {
    "x": 1251,
    "y": 766
   }
  ],
  [
   "edinburgh_147",
   {
    "x": 1266,
    "y": 767
   }
  ],
  [
   "edinburgh_15",
   {
    "x": 0,
    "y": 183
   }
  ],
  [
   "edinburgh_16",
   {
    "x": 800,
    "y": 1395
   }
  ],
  [
   "edinburgh_17",
   {
    "x": 939,
    "y": 769
   }
  ],
  [
   "edinburgh_18",
   {
    "x": 1114,
    "y": 183
   }
  ],
  [
   "edinburgh_19",
   {
    "x": 670,
    "y": 1530
   }
  ],
  [
   "edinburgh_2",
   {
    "x": 863,
    "y": 1259
   }
  ],
  [
   "edinburgh_20",
   {
    "x": 800,
    "y": 1482
   }
  ],
  [
   "edinburgh_21",
   {
    "x": 670,
    "y": 1406
   }
  ],
  [
   "edinburgh_22",
   {
    "x": 670,
    "y": 769
   }
  ],
  [
   "edinburgh_23",
   {
    "x": 1091,
    "y": 769
   }
  ],
  [
   "edinburgh_24",
   {
    "x": 543,
    "y": 490
   }
  ],
  [
   "edinburgh_25",
   {
    "x": 800,
    "y": 1305
   }
  ],
  [
   "edinburgh_26",
   {
    "x": 670,
    "y": 1044
   }
  ],
  [
   "edinburgh_27",
   {
    "x": 1262,
    "y": 768
   }
  ],
  [
   "edinburgh_28",
   {
    "x": 0,
    "y": 1228
   }
  ],
  [
   "edinburgh_29",
   {
    "x": 1716,
    "y": 955
   }
  ],
  [
   "edinburgh_3",
   {
    "x": 1404,
    "y": 761
   }
  ],
  [
   "edinburgh_30",
   {
    "x": 887,
    "y": 1475
   }
  ],
  [
   "edinburgh_31",
   {
    "x": 670,
    "y": 1661
   }
  ],
  [
   "edinburgh_32",
   {
    "x": 1453,
    "y": 955
   }
  ],
  [
   "edinburgh_33",
   {
    "x": 933,
    "y": 1468
   }
  ],
  [
   "edinburgh_34",
   {
    "x": 1554,
    "y": 432
   }
  ],
  [
   "edinburgh_35",
   {
    "x": 291,
    "y": 444
   }
  ],
  [
   "edinburgh_36",
   {
    "x": 1267,
    "y": 612
   }
  ],
  [
   "edinburgh_37",
   {
    "x": 1358,
    "y": 490
   }
  ],
  [
   "edinburgh_38",
   {
    "x": 1105,
    "y": 732
   }
  ],
  [
   "edinburgh_39",
   {
    "x": 1448,
    "y": 725
   }
  ],
  [
   "edinburgh_4",
   {
    "x": 1321,
    "y": 183
   }
  ],
  [
   "edinburgh_40",
   {
    "x": 1727,
    "y": 971
   }
  ],
  [
   "edinburgh_41",
   {
    "x": 1105,
    "y": 612
   }
  ],
  [
   "edinburgh_42",
   {
    "x": 1308,
    "y": 769
   }
  ],
  [
   "edinburgh_43",
   {
    "x": 648,
    "y": 183
   }
  ],
  [
   "edinburgh_44",
   {
    "x": 1616,
    "y": 612
   }
  ],
  [
   "edinburgh_45",
   {
    "x": 717,
    "y": 490
   }
  ],
  [
   "edinburgh_46",
   {
    "x": 958,
    "y": 0
   }
  ],
  [
   "edinburgh_47",
   {
    "x": 1526,
    "y": 955
   }
  ],
  [
   "edinburgh_48",
   {
    "x": 1683,
    "y": 1005
   }
  ],
  [
   "edinburgh_49",
   {
    "x": 1011,
    "y": 490
   }
  ],
  [
   "edinburgh_5",
   {
    "x": 1412,
    "y": 432
   }
  ],
  [
   "edinburgh_50",
   {
    "x": 1727,
    "y": 979
   }
  ],
  [
   "edinburgh_51",
   {
    "x": 1404,
    "y": 717
   }
  ],
  [
   "edinburgh_52",
   {
    "x": 800,
    "y": 1113
   }
  ],
  [
   "edinburgh_53",
   {
    "x": 933,
    "y": 1234
   }
  ],
  [
   "edinburgh_54",
   {
    "x": 1257,
    "y": 955
   }
  ],
  [
   "edinburgh_55",
   {
    "x": 933,
    "y": 1029
   }
  ],
  [
   "edinburgh_56",
   {
    "x": 1227,
    "y": 764
   }
  ],
  [
   "edinburgh_57",
   {
    "x": 1428,
    "y": 761
   }
  ],
  [
   "edinburgh_58",
   {
    "x": 1635,
    "y": 769
   }
  ],
  [
   "edinburgh_59",
   {
    "x": 0,
    "y": 730
   }
  ],
  [
   "edinburgh_6",
   {
    "x": 1517,
    "y": 490
   }
  ],
  [
   "edinburgh_60",
   {
    "x": 0,
    "y": 1607
   }
  ],
  [
   "edinburgh_61",
   {
    "x": 1554,
    "y": 479
   }
  ],
  [
   "edinburgh_62",
   {
    "x": 1038,
    "y": 330
   }
  ],
  [
   "edinburgh_63",
   {
    "x": 1716,
    "y": 971
   }
  ],
  [
   "edinburgh_64",
   {
    "x": 933,
    "y": 1119
   }
  ],
  [
   "edinburgh_65",
   {
    "x": 682,
    "y": 0
   }
  ],
  [
   "edinburgh_66",
   {
    "x": 933,
    "y": 1353
   }
  ],
  [
   "edinburgh_67",
   {
    "x": 854,
    "y": 330
   }
  ],
  [
   "edinburgh_68",
   {
    "x": 1222,
    "y": 330
   }
  ],
  [
   "edinburgh_69",
   {
    "x": 543,
    "y": 612
   }
  ],
  [
   "edinburgh_7",
   {
    "x": 1358,
    "y": 955
   }
  ],
  [
   "edinburgh_70",
   {
    "x": 1251,
    "y": 732
   }
  ],
  [
   "edinburgh_71",
   {
    "x": 593,
    "y": 432
   }
  ],
  [
   "edinburgh_72",
   {
    "x": 1633,
    "y": 330
   }
  ],
  [
   "edinburgh_73",
   {
    "x": 0,
    "y": 1440
   }
  ],
  [
   "edinburgh_74",
   {
    "x": 951,
    "y": 612
   }
  ],
  [
   "edinburgh_75",
   {
    "x": 1415,
    "y": 0
   }
  ],
  [
   "edinburgh_76",
   {
    "x": 1010,
    "y": 1680
   }
  ],
  [
   "edinburgh_77",
   {
    "x": 1735,
    "y": 979
   }
  ],
  [
   "edinburgh_78",
   {
    "x": 1258,
    "y": 766
   }
  ],
  [
   "edinburgh_79",
   {
    "x": 1442,
    "y": 727
   }
  ],
  [
   "edinburgh_8",
   {
    "x": 1267,
    "y": 717
   }
  ],
  [
   "edinburgh_80",
   {
    "x": 800,
    "y": 894
   }
  ],
  [
   "edinburgh_81",
   {
    "x": 1735,
    "y": 980
   }
  ],
  [
   "edinburgh_82",
   {
    "x": 418,
    "y": 330
   }
  ],
  [
   "edinburgh_83",
   {
    "x": 213,
    "y": 997
   }
  ],
  [
   "edinburgh_84",
   {
    "x": 1735,
    "y": 981
   }
  ],
  [
   "edinburgh_85",
   {
    "x": 1735,
    "y": 982
   }
  ],
  [
   "edinburgh_86",
   {
    "x": 246,
    "y": 730
   }
  ],
  [
   "edinburgh_87",
   {
    "x": 1264,
    "y": 758
   }
  ],
  [
   "edinburgh_88",
   {
    "x": 880,
    "y": 490
   }
  ],
  [
   "edinburgh_89",
   {
    "x": 1732,
    "y": 1005
   }
  ],
  [
   "edinburgh_9",
   {
    "x": 1358,
    "y": 578
   }
  ],
  [
   "edinburgh_90",
   {
    "x": 670,
    "y": 1293
   }
  ],
  [
   "edinburgh_91",
   {
    "x": 1055,
    "y": 1468
   }
  ],
  [
   "edinburgh_92",
   {
    "x": 1055,
    "y": 1541
   }
  ],
  [
   "edinburgh_93",
   {
    "x": 1266,
    "y": 763
   }
  ],
  [
   "edinburgh_94",
   {
    "x": 0,
    "y": 444
   }
  ],
  [
   "edinburgh_95",
   {
    "x": 670,
    "y": 612
   }
  ],
  [
   "edinburgh_96",
   {
    "x": 1266,
    "y": 764
   }
  ],
  [
   "edinburgh_97",
   {
    "x": 1214,
    "y": 490
   }
  ],
  [
   "edinburgh_98",
   {
    "x": 1262,
    "y": 766
   }
  ],
  [
   "edinburgh_99",
   {
    "x": 1055,
    "y": 1520
   }
  ]
 ],
 "parameters": {
  "bin": "BNF",
  "pack": "GuillotineBafSlas",
  "sort": "SORT_AREA"
 },
 "summary": {
  "id": "BNF/GuillotineBafSlas/SORT_AREA",
  "name": "BNF/GuillotineBafSlas/SORT_AREA",
  "place_id": "edinburgh"
 }
}